notifications/__init__.py
notifications/admin.py
notifications/apps.py
notifications/helpers.py
notifications/models.py
notifications/settings.py
notifications/signals.py
notifications/urls.py
notifications/utils.py
notifications/views.py
notifications/base/__init__.py
notifications/base/admin.py
notifications/base/models.py
notifications/locale/ru/LC_MESSAGES/django.po
notifications/migrations/0001_initial.py
notifications/migrations/0002_auto_20150224_1134.py
notifications/migrations/0003_notification_data.py
notifications/migrations/0004_auto_20150826_1508.py
notifications/migrations/0005_auto_20160504_1520.py
notifications/migrations/0006_indexes.py
notifications/migrations/0007_add_timestamp_index.py
notifications/migrations/0008_index_together_recipient_unread.py
notifications/migrations/0009_alter_notification_options_and_more.py
notifications/migrations/__init__.py
notifications/templates/notifications/list.html
notifications/templates/notifications/notice.html
notifications/templates/notifications/test_tags.html
notifications/templatetags/__init__.py
notifications/templatetags/notifications_tags.py
notifications/tests/__init__.py
notifications/tests/settings.py
notifications/tests/tests.py
notifications/tests/urls.py
notifications/tests/views.py
notifications/tests/sample_notifications/__init__.py
notifications/tests/sample_notifications/admin.py
notifications/tests/sample_notifications/apps.py
notifications/tests/sample_notifications/models.py
notifications/tests/sample_notifications/tests.py
notifications/tests/sample_notifications/migrations/0001_initial.py
notifications/tests/sample_notifications/migrations/__init__.py
notifications/tests/sample_notifications/templatetags/__init__.py
notifications/tests/sample_notifications/templatetags/notifications_tags.py
notifications/tests/templates/test_live.html
django_notifications_hq-1.8.2.dist-info/AUTHORS.txt
django_notifications_hq-1.8.2.dist-info/LICENSE.txt
django_notifications_hq-1.8.2.dist-info/METADATA
django_notifications_hq-1.8.2.dist-info/WHEEL
django_notifications_hq-1.8.2.dist-info/top_level.txt
django_notifications_hq-1.8.2.dist-info/RECORD
